# Зміст

${toc}

# Історія і мотивація

## Мотивація до вивчення Java

Мало мов можуть похвалитися тим, що їм вдалося змінити загальне уявлення про програмування. Але і в цій "елітнії" групі одна мова вирізняється з-поміж інших. ЇЇ вплив дуже швидко відчули всі програмісти. Мова, звичайно ж, йдеться про Java. Мова Java багато років залишається в топах.

## Області застосування Java

## Історія винекнення

Java  - сильно типізований об'єктно-орієнтована мова програмування. Клас мови мультипарадигмальності: об'єктно-орієнтована, структурний, імперативний, компонентно-орієнтований, узагальнений, рефлективний, функціональний.

Мова Java була розроблена компанією Sun Microsystems, творцем якої був Джеймс Гослінг, і випущена в 1995 році в якості основних компонентів компанії Sun Microsystems - Java платформ (Java 1.0 [J2SE])

Спочатку мова називалася Oak ( «Дуб»), розроблялася для програмування побутових електронних пристроїв. Згодом вона була перейменована в Java і стала використовуватися для написання клієнтських додатків і серверного програмного забезпечення. Названа на честь марки кави Java, яка, в свою чергу, отримала найменування однойменного острова (Ява), тому на офіційній емблемі мови зображена чашка з гарячою кавою(рис. 1). Існує й інша версія походження назви мови, пов'язана з алюзією на кавову-машину як приклад побутового пристрою, для програмування якого спочатку мова створювався. Відповідно до етимологією в російськомовній літературі з кінця двадцятого і до перших років ХХІ століття назва мови нерідко переводилося як Ява, а не як транскрибація, як це стало загальноприйнятим пізніше.

# Версіонування і різновиди платформи

# Як працює Java?

Програми на Java транслюються в байт-код Java, який виконується віртуальною машиною Java (JVM) – програмою, яка обробляє байт-код і передає інструкції обладнанню як інтерпретатор.

Байт-код або байтко́д (англ. byte-code), іноді також використовується термін псевдокод — машинно-незалежний код низького рівня, що генерується транслятором і виконуваний інтерпретатором. Більшість інструкцій байт-коду еквівалентні одній або кільком командам асемблера. Трансляція в байт-код займає проміжне положення між компіляцією в машинний код і інтерпретацією[3].

Байт-код називається так тому, що довжина кожного коду операції — один байт, але довжина коду команди різна. Кожна інструкція є однобайтовим кодом операції від 0 до 255, за яким слідують такі параметри, як регістри або адреси пам'яті. Це в типовому випадку, але специфікація байт-коду значно відрізняється в мовах програмування.
Java:

```java
outer:
for (int i = 2; i < 1000; i++) {
    for (int j = 2; j < i; j++) {
        if (i % j == 0)
            continue outer;
    }
  System.out.println (i);
}
```

Байт-код:

```
 0:   iconst_2
 1:   istore_1
 2:   iload_1
 3:   sipush  1000
 6:   if_icmpge       44
 9:   iconst_2
 10:  istore_2
 11:  iload_2
 12:  iload_1
 13:  if_icmpge       31
 16:  iload_1
 17:  iload_2
 18:  irem
 19:  ifne    25
 22:  goto    38
 25:  iinc    2, 1
 28:  goto    11
 31:  getstatic       #84; //Field java/lang/System.out:Ljava/io/PrintStream;
 34:  iload_1
 35:  invokevirtual   #85; //Method java/io/PrintStream.println:(I)V
 38:  iinc    1, 1
 41:  goto    2
 44:  return
```

Перевагою подібного способу виконання програм є повна незалежність байт-коду від операційної системи і обладнання, що дозволяє виконувати Java-додатки на будь-якому пристрої, для якого існує відповідна віртуальна машина. Іншою важливою особливістю технології Java є гнучка система безпеки, в рамках якої виконання програми повністю контролюється віртуальною машиною. Будь-які операції, які перевищують встановлені повноваження програми (наприклад, спроба несанкціонованого доступу до даних або з'єднання з іншим комп'ютером), викликають негайне переривання.

Часто до недоліків концепції віртуальної машини відносять зниження продуктивності.

Ряд удосконалень дещо збільшив швидкість виконання програм на Java:
  • застосування технології трансляції байт-коду в машинний код безпосередньо під час роботи програми (JIT-технологія) з можливістю збереження версій класу в машинному коді;
  • широке використання переносного орієнтованого коду (native-код) в стандартних бібліотеках;
  • апаратні засоби, що забезпечують прискорену обробку байт-коду (наприклад, технологія Jazelle, підтримувана деякими процесорами архітектури ARM).
Jazelle DBX (англ. Direct Bytecode eXecution, «безпосереднє виконання байткоду») — технологія, що дозволяє виконання інструкцій байт-коду Java на апаратному рівні. Реалізована у деяких процесорах архітектури ARM[4].

## JVM & JDK

Для виконання програм написаних на Java нам знадобиться JVM, яка входить в поставку JRE, а для їх розробки JDK.

• JVM(Java Virtual Machine) - середовище ("віртуальне"), в якому виконується  скомпільований код.
• 	JRE(Java Runtime Environment). Просто пакет, який включає в себе JVM і мінімальний набір бібліотек для роботи програм. І ще браузерні плагін, де будуть виконуватися аплети.
• 	JDK(Java Development Kit) - це вже повноцінний набір бібліотек і інструментів для створення, компіляції та дебага програм. Включає в себе jre.

# Домашнє завдання



# Контрольні запитання